dbt_heartbeat/__init__.py
dbt_heartbeat/main.py
dbt_heartbeat-0.2.4.dist-info/licenses/LICENCE.txt
utils/__init__.py
utils/api/__init__.py
utils/api/dbt_cloud_api.py
utils/api/job_monitor.py
utils/config/__init__.py
utils/config/env.py
utils/display/__init__.py
utils/display/console_output.py
utils/notifications/__init__.py
utils/notifications/run_notifs.py
utils/version/__init__.py
utils/version/version_check.py
dbt_heartbeat-0.2.4.dist-info/METADATA
dbt_heartbeat-0.2.4.dist-info/WHEEL
dbt_heartbeat-0.2.4.dist-info/entry_points.txt
dbt_heartbeat-0.2.4.dist-info/top_level.txt
dbt_heartbeat-0.2.4.dist-info/RECORD
