Metadata-Version: 2.4
Name: dbt-heartbeat
Version: 0.2.4
Summary: A CLI tool to monitor individual dbt Cloud run jobs and receive OS notifications when they complete.
Author-email: Jairus Martinez <jairusmartinez@gmail.com>
License-Expression: MIT
Project-URL: Source, https://github.com/jairus-m/dbt-heartbeat
Keywords: dbt,dbt-cloud,cli,notifications
Classifier: Development Status :: 4 - Beta
Classifier: Environment :: Console
Classifier: Intended Audience :: Developers
Classifier: Operating System :: MacOS
Classifier: Topic :: Software Development :: Libraries :: Python Modules
Requires-Python: >=3.8
License-File: LICENCE.txt
Requires-Dist: requests==2.31.0
Requires-Dist: python-dotenv==1.0.0
Requires-Dist: rich==13.7.0
Requires-Dist: pync==2.0.3
Requires-Dist: win10toast==0.9; sys_platform == "win32"
Dynamic: license-file
